btrdbextras/__init__.py
btrdbextras/conn.py
btrdbextras/dq.py
btrdbextras/eventproc/__init__.py
btrdbextras/eventproc/eventproc.py
btrdbextras/eventproc/protobuff/__init__.py
btrdbextras/eventproc/protobuff/api_pb2.py
btrdbextras/eventproc/protobuff/api_pb2_grpc.py
btrdbextras-5.11.9.dist-info/LICENSE.txt
btrdbextras-5.11.9.dist-info/METADATA
btrdbextras-5.11.9.dist-info/WHEEL
btrdbextras-5.11.9.dist-info/entry_points.txt
btrdbextras-5.11.9.dist-info/top_level.txt
btrdbextras-5.11.9.dist-info/RECORD
