Metadata-Version: 2.1
Name: btrdbextras
Version: 5.11.9
Summary: Enhancements additional features to interact with the Berkeley Tree Database
Home-page: https://btrdbextras.readthedocs.io/en/latest/
Author: Allen Leis
Author-email: allen@pingthings.io
Maintainer: Allen Leis
Maintainer-email: allen@pingthings.io
License: BSD-3-Clause
Download-URL: https://github.com/PingThingsIO/btrdbextras/tarball/vv5.11.9
Project-URL: Documentation, https://btrdbextras.readthedocs.io/en/latest/
Project-URL: Download, https://github.com/PingThingsIO/btrdbextras/tarball/vv5.11.9
Project-URL: Source, https://github.com/PingThingsIO/btrdbextras
Project-URL: Tracker, https://github.com/PingThingsIO/btrdbextras/issues
Keywords: btrdb,timeseries,database
Platform: UNKNOWN
Classifier: Development Status :: 5 - Production/Stable
Classifier: Intended Audience :: Developers
Classifier: Intended Audience :: Information Technology
Classifier: Intended Audience :: Science/Research
Classifier: License :: OSI Approved :: BSD License
Classifier: Natural Language :: English
Classifier: Operating System :: OS Independent
Classifier: Programming Language :: Python
Classifier: Programming Language :: Python :: 3.6
Classifier: Programming Language :: Python :: 3.7
Classifier: Programming Language :: Python :: 3.8
Classifier: Topic :: Database
Classifier: Topic :: Software Development :: Libraries :: Python Modules
Requires-Python: >=3.6, <4
Requires-Dist: grpcio (>=1.16.1)
Requires-Dist: grpcio-tools (>=1.16.1)
Requires-Dist: dill (==0.3.2)
Requires-Dist: btrdb (>=5.11.7)
Requires-Dist: tabulate (==0.8.9)
Requires-Dist: certifi
Requires-Dist: sphinx-glpi-theme
